japanize_matplotlib_modern/__init__.py
japanize_matplotlib_modern/japanize_matplotlib.py
japanize_matplotlib_modern/fonts/IPA_Font_License_Agreement_v1.0.txt
japanize_matplotlib_modern/fonts/Readme_ipaexg00301.txt
japanize_matplotlib_modern/fonts/ipaexg.ttf
japanize_matlibplot_modern-0.1.4.dist-info/METADATA
japanize_matlibplot_modern-0.1.4.dist-info/WHEEL
japanize_matlibplot_modern-0.1.4.dist-info/licenses/LICENSE
japanize_matlibplot_modern-0.1.4.dist-info/RECORD
