Metadata-Version: 2.4
Name: japanize-matlibplot-modern
Version: 0.1.4
Summary: matplotlib を日本語表示に対応させます
License-File: LICENSE
Requires-Python: >=3.5
Requires-Dist: matplotlib>=3.0.0
